Itomori/__init__.py
Itomori/main.py
Itomori/style.tcss
Itomori/components/AboutScreen.py
Itomori/components/AddNoteInputBox.py
Itomori/components/InfoWhereSaved.py
Itomori/components/LicenseScreen.py
Itomori/components/LicenseText.py
Itomori/components/LogoText.py
Itomori/components/RecentNotes.py
Itomori/components/ViewRawNotes.py
Itomori/components/WelcomeTextRender.py
Itomori/components/__init__.py
Itomori/themes/YourNameTheme.py
itomori-1.1.1.dist-info/licenses/LICENSE
itomori-1.1.1.dist-info/METADATA
itomori-1.1.1.dist-info/WHEEL
itomori-1.1.1.dist-info/entry_points.txt
itomori-1.1.1.dist-info/top_level.txt
itomori-1.1.1.dist-info/RECORD
