Metadata-Version: 2.4
Name: Itomori
Version: 1.1.1
Summary: Blazingly fast, minimalistic quick Note taking TUI app. Easy to store, run, share.
Author-email: Ahum Maitra <theahummaitra@gmail.com>
License-Expression: GPL-3.0-only
Project-URL: Homepage, https://itomori.vercel.app/
Project-URL: Documentation, https://itomoridocs.vercel.app/
Project-URL: Repository, https://github.com/TheAhumMaitra/Itomori
Keywords: TUI app,Note taker,Textual app,Quick note taking app
Requires-Python: >=3.12
License-File: LICENSE
Requires-Dist: textual[syntax]>=6.6.0
Requires-Dist: textual-dev>=1.8.0
Requires-Dist: loguru>=0.7.3
Requires-Dist: tinydb>=4.8.2
Requires-Dist: arrow>=1.4.0
Requires-Dist: pyjokes>=0.8.3
Requires-Dist: ruff>=0.14.6
Requires-Dist: rich>=14.2.0
Requires-Dist: pytest>=9.0.1
Requires-Dist: mypy>=1.18.2
Provides-Extra: dev
Requires-Dist: maturin>=1.10.2; extra == "dev"
Requires-Dist: mkdocs-material>=9.7.0; extra == "dev"
Dynamic: license-file
